parsevro/__init__.py
parsevro/parsevro.py
updatevro/__init__.py
updatevro/updatevro.py
vroParse-0.3.2.dist-info/LICENSE
vroParse-0.3.2.dist-info/METADATA
vroParse-0.3.2.dist-info/WHEEL
vroParse-0.3.2.dist-info/entry_points.txt
vroParse-0.3.2.dist-info/top_level.txt
vroParse-0.3.2.dist-info/RECORD
