Metadata-Version: 2.1
Name: vroParse
Version: 0.3.2
Summary: Parses scriptable tasks out of vRO Workflow XML, saves them as discrete files for editing and SCC, and imports edits in code back into XML.
Home-page: https://github.com/nhlpens66/vroParse
Author: Jim Sadlek
Author-email: sadlekj@vmware.com
License: MIT
Keywords: vmware,build-tools,vrealize,vra,vro,parse,xml
Platform: UNKNOWN
Classifier: Development Status :: 3 - Alpha
Classifier: Intended Audience :: Developers
Classifier: License :: OSI Approved :: MIT License
Classifier: Natural Language :: English
Classifier: Operating System :: OS Independent
Classifier: Programming Language :: Python
Classifier: Programming Language :: Python :: 3
Classifier: Programming Language :: Python :: 3.8
Requires-Python: >=3.5
